pyAnaf/__init__.py
pyAnaf/api.py
pyAnaf/console.py
pyAnaf/models.py
pyAnaf-0.0.3.dist-info/AUTHORS
pyAnaf-0.0.3.dist-info/LICENSE
pyAnaf-0.0.3.dist-info/METADATA
pyAnaf-0.0.3.dist-info/WHEEL
pyAnaf-0.0.3.dist-info/entry_points.txt
pyAnaf-0.0.3.dist-info/top_level.txt
pyAnaf-0.0.3.dist-info/RECORD
